tblu_module_so/__init__.py
tblu_module_so/tblu_module_so.py
tblu_module_so-0.1.4.dist-info/METADATA
tblu_module_so-0.1.4.dist-info/RECORD
tblu_module_so-0.1.4.dist-info/WHEEL
tblu_module_so-0.1.4.dist-info/top_level.txt
