Metadata-Version: 2.1
Name: tblu-module-so
Version: 0.1.4
Summary: Module Python for SO informations
Home-page: https://github.com/TBlu-Company/tblu_module_so
Author: TBlu-Company
Author-email: dev@tblu.com.br
License: MIT license
Keywords: tblu_module_so
Platform: UNKNOWN
Classifier: Development Status :: 2 - Pre-Alpha
Classifier: Intended Audience :: Developers
Classifier: License :: OSI Approved :: MIT License
Classifier: Natural Language :: English
Classifier: Programming Language :: Python :: 2
Classifier: Programming Language :: Python :: 2.7
Classifier: Programming Language :: Python :: 3
Classifier: Programming Language :: Python :: 3.4
Classifier: Programming Language :: Python :: 3.5
Classifier: Programming Language :: Python :: 3.6
Classifier: Programming Language :: Python :: 3.7
Requires-Dist: psutil (>=5.4.6)
Requires-Dist: py-cpuinfo (>=4.0.0)
